scrapyx_stormproxies/__init__.py
scrapyx_stormproxies/stormproxies.py
scrapyx_stormproxies-0.1.1.dist-info/METADATA
scrapyx_stormproxies-0.1.1.dist-info/WHEEL
scrapyx_stormproxies-0.1.1.dist-info/top_level.txt
scrapyx_stormproxies-0.1.1.dist-info/RECORD
