Metadata-Version: 2.1
Name: scrapyx-stormproxies
Version: 0.1.1
Summary: Stormproxies middleware for Scrapy
Home-page: https://github.com/tubndgit/scrapyx-stormproxies
Author: Henry B.
Author-email: tubnd.younet@gmail.com
License: MIT
Download-URL: https://github.com/tubndgit/scrapyx-stormproxies/archive/master.zip
Platform: UNKNOWN
Requires-Python: >=2.7
